CHANGELOG.txt
LICENSE.txt
MANIFEST.in
Readme.txt
SETUP.py
__init__.py
setup.py
Basic_Calculator_2.0.egg-info/PKG-INFO
Basic_Calculator_2.0.egg-info/SOURCES.txt
Basic_Calculator_2.0.egg-info/dependency_links.txt
Basic_Calculator_2.0.egg-info/top_level.txt