Metadata-Version: 1.1
Name: Basic-Calculator-2.0
Version: 0.0.1
Summary: My First Python Package
Home-page: UNKNOWN
Author: Neelansh Agarwal
Author-email: py4e@hotmail.com
License: MIT
Keywords: Calculator
Platform: UNKNOWN
Classifier: Development Status :: 5 - Production/Stable
Classifier: Intended Audience :: Education
Classifier: Operating System :: Microsoft :: Windows :: Windows 10
Classifier: License :: OSI Approved :: MIT License
Classifier: Programming Language :: Python :: 3
